speckit/__init__.py
speckit/analysis.py
speckit/core.py
speckit/dsp.py
speckit/flattop.py
speckit/noise.py
speckit/plotting.py
speckit/schedulers.py
speckit/systems.py
speckit/utils.py
speckit-1.0.2.dist-info/licenses/AUTHORS
speckit-1.0.2.dist-info/licenses/LICENSE
speckit-1.0.2.dist-info/METADATA
speckit-1.0.2.dist-info/WHEEL
speckit-1.0.2.dist-info/top_level.txt
speckit-1.0.2.dist-info/RECORD
