Metadata-Version: 2.4
Name: speckit
Version: 1.0.2
Summary: A Python Toolkit for Dynamic-Resolution Spectral Analysis.
Author: Gerhard Heinzel
Author-email: Miguel Dovale <mikedovale@pm.me>
License-Expression: BSD-3-Clause
Project-URL: Homepage, https://github.com/mdovale/spectools
Project-URL: Repository, https://github.com/mdovale/spectools
Project-URL: Issues, https://github.com/mdovale/spectools/issues
Classifier: Programming Language :: Python :: 3
Classifier: Operating System :: OS Independent
Classifier: Intended Audience :: Science/Research
Classifier: Topic :: Scientific/Engineering :: Physics
Requires-Python: >=3.9
License-File: LICENSE
License-File: AUTHORS
Requires-Dist: numpy
Requires-Dist: scipy
Requires-Dist: pandas
Requires-Dist: control
Requires-Dist: matplotlib
Requires-Dist: numba
Requires-Dist: tqdm
Requires-Dist: py7zr
Provides-Extra: dev
Requires-Dist: pytest; extra == "dev"
Requires-Dist: build; extra == "dev"
Requires-Dist: twine; extra == "dev"
Requires-Dist: ruff; extra == "dev"
Dynamic: license-file
